cloudpathlib/__init__.py
cloudpathlib/anypath.py
cloudpathlib/client.py
cloudpathlib/cloudpath.py
cloudpathlib/exceptions.py
cloudpathlib/azure/__init__.py
cloudpathlib/azure/azblobclient.py
cloudpathlib/azure/azblobpath.py
cloudpathlib/gs/__init__.py
cloudpathlib/gs/gsclient.py
cloudpathlib/gs/gspath.py
cloudpathlib/local/__init__.py
cloudpathlib/local/localclient.py
cloudpathlib/local/localpath.py
cloudpathlib/local/implementations/__init__.py
cloudpathlib/local/implementations/azure.py
cloudpathlib/local/implementations/gs.py
cloudpathlib/local/implementations/s3.py
cloudpathlib/s3/__init__.py
cloudpathlib/s3/s3client.py
cloudpathlib/s3/s3path.py
tests/__init__.py
tests/conftest.py
tests/test_anypath.py
tests/test_azure_specific.py
tests/test_client.py
tests/test_cloudpath_file_io.py
tests/test_cloudpath_instantiation.py
tests/test_cloudpath_internal.py
tests/test_cloudpath_manipulation.py
tests/test_cloudpath_upload_copy.py
tests/test_gs_specific.py
tests/test_integrations.py
tests/test_local.py
tests/test_s3_specific.py
elucidatacloudpathlib-0.6.6.dist-info/LICENSE
elucidatacloudpathlib-0.6.6.dist-info/METADATA
elucidatacloudpathlib-0.6.6.dist-info/WHEEL
elucidatacloudpathlib-0.6.6.dist-info/top_level.txt
elucidatacloudpathlib-0.6.6.dist-info/RECORD
