Metadata-Version: 2.1
Name: elucidatacloudpathlib
Version: 0.6.6
Summary: pathlib-style classes for cloud storage services
Home-page: https://github.com/drivendataorg/cloudpathlib
Author: DrivenData
Author-email: info@drivendata.org
License: UNKNOWN
Project-URL: Bug Tracker, https://github.com/drivendataorg/cloudpathlib/issues
Project-URL: Documentation, https://cloudpathlib.drivendata.org/
Project-URL: Source Code, https://github.com/drivendataorg/cloudpathlib
Platform: UNKNOWN
Classifier: Intended Audience :: Developers
Classifier: License :: OSI Approved :: MIT License
Classifier: Operating System :: OS Independent
Classifier: Programming Language :: Python :: 3
Classifier: Programming Language :: Python :: 3.6
Classifier: Programming Language :: Python :: 3.7
Classifier: Programming Language :: Python :: 3.8
Requires-Python: >=3.6
Requires-Dist: importlib-metadata ; python_version < "3.8"
Provides-Extra: all
Requires-Dist: azure-storage-blob (>=12) ; extra == 'all'
Requires-Dist: google-cloud-storage ; extra == 'all'
Requires-Dist: boto3 ; extra == 'all'
Provides-Extra: azure
Requires-Dist: azure-storage-blob (>=12) ; extra == 'azure'
Provides-Extra: gs
Requires-Dist: google-cloud-storage ; extra == 'gs'
Provides-Extra: s3
Requires-Dist: boto3 ; extra == 's3'
